flashmoe/__init__.py
flashmoe/main.py
flashmoe-0.0.1.dev0.dist-info/METADATA
flashmoe-0.0.1.dev0.dist-info/WHEEL
flashmoe-0.0.1.dev0.dist-info/top_level.txt
flashmoe-0.0.1.dev0.dist-info/RECORD
