Metadata-Version: 2.2
Name: flashmoe
Version: 0.0.1.dev0
Summary: Sample Python package
Author-email: Zhan Lu <lausannel666@gmail.com>
License: MIT
